{
  "project_info": {
    "project_number": "330909370958",
    "project_id": "chatapp-dd1c7",
    "storage_bucket": "chatapp-dd1c7.appspot.com"
  },
  "client": [
    {
      "client_info": {
        "mobilesdk_app_id": "1:330909370958:android:cdea5815577252b980111f",
        "android_client_info": {
          "package_name": "com.example.chatapp"
        }
      },
      "oauth_client": [
        {
          "client_id": "330909370958-j2et57uceh0b5sc3a2gdvkur6iqr7ssr.apps.googleusercontent.com",
          "client_type": 3
        }
      ],
      "api_key": [
        {
          "current_key": "AIzaSyC-FtyuWYT7kTKLiK0gX_nThZSqKWTbhJc"
        }
      ],
      "services": {
        "appinvite_service": {
          "other_platform_oauth_client": [
            {
              "client_id": "330909370958-j2et57uceh0b5sc3a2gdvkur6iqr7ssr.apps.googleusercontent.com",
              "client_type": 3
            }
          ]
        }
      }
    }
  ],
  "configuration_version": "1"
}